Lab5_part4_CPU module/Part1_alu.v
// ALU MODULE
module alu(DATA1, DATA2, RESULT, SELECT, ZERO);

    input signed [7:0] DATA1, DATA2;                     // Two inputs of 8 bit length
    input signed [2:0] SELECT;                           // An input of 3 bit length
    output signed [7:0] RESULT;                          // Output of 8 bit length with the arithmetic calcultion
    output  ZERO;                                        // Output with the beq condition for data1 and data2 being equal or not

    wire signed [7:0] ForwardOut,AddOut,AndOut,OrOut,MultOut,f,g,h;                   // Eight 8-bit wires to store the outputs of the modules
    wire signed [7:0] out;                                                      // A wire output to hold the output of the MUX

    // Instantiate the functional unit modules
    // These modules are run whenever any one of the parameters in the module sensitivity list changes.

    FORWARD F1 (DATA2, ForwardOut);                             // #1 delay
    ADD A1 (DATA1, DATA2, AddOut);                              // #2 delay
    AND A2 (DATA1, DATA2, AndOut);                              // #1 delay
    OR O1 (DATA1, DATA2, OrOut);                                // #1 delay

    // Instantiate the MUX to choose the right output
    // The MUX module is triggered when any one of the parameters in the module list is changed
    MUX_8X3 M1 (ForwardOut,AddOut,AndOut,OrOut,MultOut,f,g,h,SELECT, out);

    // Assign the selected output to RESULT according to "SELECT"
    assign RESULT = out;

    // The branch if equal module which sets the value of the output zero to 1/0
    beq BEQ(ZERO, RESULT, SELECT);
endmodule

// FORWARD module
module FORWARD(DATA2, out);

    input signed [7:0] DATA2;                          // 8-bit input
    output signed [7:0] out;                           // 8-bit output

    assign #1 out = DATA2;                      // Assign DATA2 to the output with a 1 unit delay

endmodule

// ADD module
module ADD(DATA1, DATA2, out);

    input signed [7:0] DATA1, DATA2;                   // Two 8-bit inputs
    output signed [7:0] out;                           // 8-bit output
    wire signed [7:0] carry;                           // A wire to store the carry-out of the sum

    assign #2 {carry, out} = DATA1 + DATA2;        // Perform addition and assign the carry-out and sum accordingly with a 2 unit delay

endmodule

// AND module
module AND(DATA1, DATA2, out);

    input signed [7:0] DATA1, DATA2;                   // Two 8-bit inputs
    output signed [7:0] out;                           // 8-bit output

    // Perform the AND operation on every bit of the two inputs
    assign #1 out = DATA1 & DATA2;

endmodule

// OR module
module OR(DATA1, DATA2, out);

    input signed [7:0] DATA1, DATA2;                   // Two 8-bit inputs
    output signed [7:0] out;                           // 8-bit output

    // Perform the OR operation on every bit of the two inputs
    assign #1 out = DATA1 | DATA2;


endmodule

// mult module
module mult(DATA1, DATA2, out);

    input signed [7:0] DATA1, DATA2;                   // Two 8-bit inputs
    output signed [7:0] out;                           // 8-bit output

    // Multiplication using gate level modeling
    assign #1 out = DATA1 * DATA2;


endmodule

// MUX module (8x3 MUX)
module MUX_8X3(ForwardOut,AddOut,AndOut,OrOut,MultOut,f,g,h, SELECT, out);

    input signed [7:0] ForwardOut,AddOut,AndOut,OrOut,MultOut,f,g,h;                 // Eight 8-bit inputs to the MUX
    input signed[2:0] SELECT;                                                 // 3-bit select input
    output reg signed [7:0] out;                                               // 8-bit output of the mux (connected to the result port of the ALU)

    // An always block for the switch case
    always @(ForwardOut,AddOut,AndOut,OrOut,MultOut,f,g,h,SELECT)
    begin
        // The case structure
        case(SELECT)
            3'b000: out = ForwardOut;               // Forward result
            3'b001: out = AddOut;                   // ADD result
            3'b010: out = AndOut;                   // AND result
            3'b011: out = OrOut;                    // OR result
            // Reserved for future operations
            3'b100: out = MultOut;
            3'b101: out = f;
            3'b110: out = g;
            3'b111: out = h;
            default: out = 8'bxxxxxxxx;
        endcase
    end

endmodule

//Module for beq zero setting
module beq(ZERO, RESULT, SELECT);

    input signed [7:0] RESULT;                  // Get the output of the mux as an input
    input [2:0] SELECT;                         // Get the ALUOP as an input to determine if it is a subtraction                         
    output reg ZERO;                            // The output

    // An always block triggered everytime SELECT/RESULT changes
    always @(RESULT, SELECT)
    begin
        // If the subtraction is 0
        if(RESULT == 8'd0 && SELECT == 3'b001) ZERO = 1'b1;
        // For any other time
        else  ZERO = 1'b0;
    end

endmodule

Lab5_part4_CPU module/Part4_cpu.v
// // Lab5 Part3
// // Group 6 : E/18/147
// //           E/18/379

/* ************************************************************************************************************* */
module cpu(PC, INSTRUCTION, CLK, RESET);

/*****Declaration of reg/wires*****/

//inputs and outputs to the CPU 
    input [31:0]INSTRUCTION;                    //inputs Instruction
    input CLK, RESET;                           //input clock an reset
    output reg [31:0] PC;                       //outputs the next instruciton to be executed(PC) 

//PC register afetr +4
    reg [31:0] PCregister;

//PC register after the branch/jump
    reg [31:0] PCregister_JB;

//Output of the branch mux
    wire [31:0] PCvalue;

//extracted OPCODE, Read registeer1, readregister2, writing register and immediate value
    reg [2:0] READREG1, READREG2, INADDRESS;    //registers to store registers to read and write
    reg [7:0] OPCODE;
    reg signed[7:0] IMMEDIATE;
    reg signed[31:0] IMMEDIATE_JB;              //register to store an immediatee value for branch/jump instructions

//Control signal outputs of the Control Unit
    wire WRITEENABLE;                           // Input signal to the register file
    wire SUB_ADD, IMM;                          // Select signals to the two muxs
    wire JUMP, BRANCH;                          // Used in the jump/branch selection muxs                                                
    wire [2:0] ALUOP;                           // Select signal for the ALU

// The output of the AND gate which determines whether beq is taken or not    
    wire BRANCH_TAKEN;  

// The output of the OR gate to be used as the select bit of the mux
    wire SEL;                       

//register file output wire connections
    wire signed [7:0] OUT1, OUT2;   

//outputs of muxs and ALU
    wire signed[7:0] OUT2_1, OUT2_2, RESULT;
    wire ZERO;                                  // A wire to the input of the and gate
                                                // Carries a value of 1 if the subtraction is 0 (register values are equal)

//for getting 2s Complement
    reg signed[7:0] OUT2_2s;

/***BEGIN OPERATIONS***/

/***********************************************PC MODULE BEGIN****************************************************/
//synchronous always block for PC update
    always @(posedge CLK) begin
        #1                              // Unit time delay
        if (RESET) PC = 0;              //for reseting CPU and Register
        //else PC = PCregister;           //else move to next instruction
        else PC = PCvalue;           //else move to next instruction
    end    

//always block to increment the pc register value
    always @(PC) begin
        #1                              // Unit time delay
        PCregister = PC + 4;
    end

//An adder to calculate the branch/jump addresses
    always @(PCregister)
    #1
    begin
        #2 PCregister_JB = PCregister + (4*IMMEDIATE_JB);
    end 

//instantiate the beq mux
    MUX2x1PC mux_branch(PCvalue, PCregister, PCregister_JB, SEL);


/**********************************************END OF PC MODULE***************************************************/

//always block to extract instruction parts. Trigger when an instruciton is recieved.
    always @(INSTRUCTION) begin

    OPCODE = INSTRUCTION[31:24];            //extract  opcode from instruction
    INADDRESS = INSTRUCTION[23:16];         //extract writing register
    READREG1 = INSTRUCTION[15:8];           //extract Read register 1 from instruction
    READREG2 = INSTRUCTION[7:0];            //Read register 2 from instruction
    IMMEDIATE = INSTRUCTION[7:0];           //extract immediate value from instruction
    IMMEDIATE_JB = $signed(INSTRUCTION[23:16]);      //extract the immediate value for j/beq instructions if any and sign extend it

    end


//initiating control unit
    ControlUnit CU( WRITEENABLE, ALUOP, SUB_ADD, IMM, JUMP, BRANCH, OPCODE);

//creating register file object
    reg_file register(RESULT, OUT1, OUT2, INADDRESS, READREG1, READREG2, WRITEENABLE, CLK, RESET);

//always block to get 2s Complement. The always block is triggered whenever the OUT2 changes
    always @(OUT2) begin
        #1                                      //delay 1 seconds
        OUT2_2s = ~OUT2 + 8'd1;                 //increment by 1 to get 2s complement
    end

//choosing 2s complement
    MUX2x1 Mux1(OUT2_1, OUT2, OUT2_2s, SUB_ADD);

//chosing immediate value or  register value
    MUX2x1 Mux2(OUT2_2, OUT2_1, IMMEDIATE, IMM);

//feeding result to ALU. Create an alu object
    alu ALU(OUT1, OUT2_2, RESULT, ALUOP, ZERO);               //delay of #2 maximum

//And gate for the branch instruction
    and A1(BRANCH_TAKEN, BRANCH, ZERO);

// Or gate to see for a jump or a branch
    or O1 (SEL, JUMP, BRANCH_TAKEN);

endmodule

//module for Control unit
module ControlUnit (WRITEENABLE, ALUOP, SUB_ADD, IMM, JUMP, BRANCH, OPCODE);

//Output control signals   
    output reg SUB_ADD,IMM, WRITEENABLE, JUMP, BRANCH;
    output reg [2:0] ALUOP;

//Input signal
    input [7:0] OPCODE;

//always block to set ALUOP
    always @(OPCODE) begin
        WRITEENABLE = 0;
        #1                          //delay of 1 time unit
        case(OPCODE)
        8'b00000010: ALUOP = 3'b001;        //add instruction
        8'b00000011: ALUOP = 3'b001;        //sub instruction
        8'b00000100: ALUOP = 3'b010;        //and instruction
        8'b00000101: ALUOP = 3'b011;        //or instruction
        8'b00000000: ALUOP = 3'b000;        //loadi instruction
        8'b00000001: ALUOP = 3'b000;        //mov instruction
        8'b00000111: ALUOP = 3'b001;        //beq instruction
        8'b00001100: ALUOP = 3'b001;        //bne instruction
        8'b00001101: ALUOP = 3'b100;        //mult instruction
        default:  ALUOP = 3'bxxx;           //default

        endcase

//for sub instruction SUB_ADD=1 for add SUB_ADD=0
    if (OPCODE==8'b00000011 || OPCODE == 8'b00000111) SUB_ADD=1;
    else SUB_ADD=0;

//for loadi IMM=1 else IMM=0
    if(OPCODE==8'b00000000) IMM=1;
    else IMM=0;

//for beq instruction
    if(OPCODE==8'b00000111) BRANCH=1;
    else BRANCH = 0;

//for J instruction
    if(OPCODE==8'b00000110) JUMP=1;
    else JUMP = 0;

//ready to write to register at next positive clock edge
    if(OPCODE==8'b00000110||OPCODE==8'b00000111) WRITEENABLE = 0;
    else WRITEENABLE = 1;


    end
endmodule


//2x1 MUX module- for 8 bit inputs and outputs
module MUX2x1(output1, input1, input2, select);
    
    //inputs - select bit and two inputs
    input [7:0]input1, input2;
    input select;        

    output reg [7:0]output1;                     //chosen input to be sent as the output

    //case block to implement the MUX
    always @(input1, input2, select) begin
      case (select)
        1'b0: output1 = input1;          //first choice  
        1'b1: output1 = input2;          //second choice
        
    endcase  
    end

endmodule

//2x1 MUX module- for 32 bit inputs and outputs
module MUX2x1PC(output1, input1, input2, select);
    
    //inputs - select bit and two inputs
    input [31:0]input1, input2;
    input select;        

    output reg [31:0]output1;                     //chosen input to be sent as the output

    //case block to implement the MUX
    always @(input1, input2, select) begin
      case (select)
        1'b0: output1 = input1;          //first choice  
        1'b1: output1 = input2;          //second choice
        
    endcase  
    end

endmodule

Lab5_part4_CPU module/Part2_reg_file.v
//module for register file
module reg_file(IN, OUT1, OUT2, INADDRESS, OUT1ADDRESS, OUT2ADDRESS, WRITE, CLK, RESET);

    //declaring wires/registers
    input [7:0] IN;                                     //input write port
    input [2:0] INADDRESS,OUT1ADDRESS,OUT2ADDRESS;      //input writing address, reading addresses
    input WRITE, CLK, RESET;                            //input control signals
    output reg signed[7:0]OUT1,OUT2;                              //output read registers
    
    reg signed [7:0] register [0:7];        //array of words representing the register(8x8)

    integer i;         //integer to iterate through the register. To reset using for loop

    //Always block to read the register. (Asynchronous) 
    //Sensitive list includes input addresses, last register(to indicate reseting) and writing address
    //Whenever register values are updated this always() block executes
    always @(OUT1ADDRESS, OUT2ADDRESS, register[7], register[INADDRESS]) begin        
        #2                         //read delay of #2
        OUT1 = register[OUT1ADDRESS];       //read value in register specified and set to output 1
        OUT2 = register[OUT2ADDRESS];       //read value in register specified and set to output 2
    end

    //Always block to reset register and write to register. (Synchronous)
    always @(posedge CLK) begin

        //if RESET signal is high, clear all registers to 0
        if(RESET) begin
        #1                          //reset delay

        for(i=0;i<8;i=i+1) begin      //for loop to iterate over the registers stored as an array of words
            register[i]=8'd0;       //set registers to zero
        end 
        end

        //if WRITE signal is high, write input value to register
        if((!RESET)&&WRITE) begin 
        #1                          //write delay
        register[INADDRESS]=IN;     //write input value into the given register
        end  
    end

    initial begin
        $dumpfile("cpu_wavedata.vcd");
        for(i=0;i<8;i = i+1)
            $dumpvars(1,register[i]);
    end

    //printing the register 
    initial begin
      #1 $display("Reg Index:\treg0\treg1\treg2\treg3\treg4\treg5\treg6\treg7"); 
        $display("----------------------------------------------------------------------------------------"); 
       $monitor("Value:    \t%d\t%d\t%d\t%d\t%d\t%d\t%d\t%d",register[0],register[1],register[2],register[3],register[4],register[5],register[6],register[7]);
    end
endmodule

Lab5_part4_CPU module/cpu_tb.v
// Computer Architecture (CO224) - Lab 05
// Design: Testbench of Integrated CPU of Simple Processor
// Author: Isuru Nawinne

module cpu_tb;

    reg CLK, RESET;
    wire [31:0] PC;
    reg [31:0] INSTRUCTION;
    //integer i;
    /* 
    ------------------------
     SIMPLE INSTRUCTION MEM
    ------------------------
    */
    
    // TODO: Initialize an array of registers (8x1024) named 'instr_mem' to be used as instruction memory

    reg [7:0] instr_mem [0:1023];                   // Memory allocated for 1024 words
                                                    // 256 Instructions (256 instructions * 4 words per instruction = 1024 words)

    // TODO: Create combinational logic to support CPU instruction fetching, given the Program Counter(PC) value 
    //       (make sure you include the delay for instruction fetching here)
    
    // Intsruction fetching is done when ever the PC register is updated
    always @(PC) begin
        #2                                          // Instruction fetching delay
        // Concatenate 4 words to form an instruction
        INSTRUCTION = {instr_mem[PC],instr_mem[PC+1],instr_mem[PC+2],instr_mem[PC+3]};
        //INSTRUCTION = {instr_mem[PC+3],instr_mem[PC+2],instr_mem[PC+1],instr_mem[PC]};

    end

    initial
    begin
        // Initialize instruction memory with the set of instructions you need execute on CPU
        
        // METHOD 1: manually loading instructions to instr_mem
        {instr_mem[10'd3], instr_mem[10'd2], instr_mem[10'd1], instr_mem[10'd0]} = 32'b00000010000000000000001000000000;
        {instr_mem[10'd7], instr_mem[10'd6], instr_mem[10'd5], instr_mem[10'd4]} = 32'b00000000000000000000011000000000;
        {instr_mem[10'd11], instr_mem[10'd10], instr_mem[10'd9], instr_mem[10'd8]} = 32'b00001010000000000000000100000000;
        {instr_mem[10'd15], instr_mem[10'd14], instr_mem[10'd13], instr_mem[10'd12]} = 32'b00000010000001100000011000000010;
        {instr_mem[10'd19], instr_mem[10'd18], instr_mem[10'd17], instr_mem[10'd16]} = 32'b00000001000001100000000100000111;
        {instr_mem[10'd23], instr_mem[10'd22], instr_mem[10'd21], instr_mem[10'd20]} = 32'b00000000000000001111110100000110;
        {instr_mem[10'd27], instr_mem[10'd26], instr_mem[10'd25], instr_mem[10'd24]} = 32'b01100011000000000000011100000000;
        
        // METHOD 2: loading instr_mem content from instr_mem.mem file
        //$readmemb("instr_mem.mem", instr_mem);
    
    end
    
    /* 
    -----
     CPU
    -----
    */
    cpu mycpu(PC, INSTRUCTION, CLK, RESET);

    initial
    begin
    
        // generate files needed to plot the waveform using GTKWave
        $dumpfile("cpu_wavedata.vcd");
		$dumpvars(0, cpu_tb);
        
        CLK = 1'b0;
        RESET = 1'b0;
        
        // TODO: Reset the CPU (by giving a pulse to RESET signal) to start the program execution
        #2
        RESET = 1'b1;

        #5
        RESET = 1'b0;

        // #43                                                     // 50th time unit: Another reset signal to restart the program
        // RESET = 1'b1;

        // #4
        // RESET = 1'b0;
        
        // finish simulation after some time
        #500
        $finish;

        
    end
    
    // clock signal generation
    always
        #4 CLK = ~CLK;
    
endmodule

Lab5_part4_CPU module/cpu_wavedata.vcd
$date
	Tue Feb 01 23:55:13 2022
$end
$version
	Icarus Verilog
$end
$timescale
	1s
$end
$scope module cpu_tb $end
$scope module mycpu $end
$scope module register $end
$var reg 8 ! \register[0] [7:0] $end
$upscope $end
$upscope $end
$upscope $end
$scope module cpu_tb $end
$scope module mycpu $end
$scope module register $end
$var reg 8 " \register[1] [7:0] $end
$upscope $end
$upscope $end
$upscope $end
$scope module cpu_tb $end
$scope module mycpu $end
$scope module register $end
$var reg 8 # \register[2] [7:0] $end
$upscope $end
$upscope $end
$upscope $end
$scope module cpu_tb $end
$scope module mycpu $end
$scope module register $end
$var reg 8 $ \register[3] [7:0] $end
$upscope $end
$upscope $end
$upscope $end
$scope module cpu_tb $end
$scope module mycpu $end
$scope module register $end
$var reg 8 % \register[4] [7:0] $end
$upscope $end
$upscope $end
$upscope $end
$scope module cpu_tb $end
$scope module mycpu $end
$scope module register $end
$var reg 8 & \register[5] [7:0] $end
$upscope $end
$upscope $end
$upscope $end
$scope module cpu_tb $end
$scope module mycpu $end
$scope module register $end
$var reg 8 ' \register[6] [7:0] $end
$upscope $end
$upscope $end
$upscope $end
$scope module cpu_tb $end
$scope module mycpu $end
$scope module register $end
$var reg 8 ( \register[7] [7:0] $end
$upscope $end
$upscope $end
$upscope $end
$scope module cpu_tb $end
$var wire 32 ) PC [31:0] $end
$var reg 1 * CLK $end
$var reg 32 + INSTRUCTION [31:0] $end
$var reg 1 , RESET $end
$scope module mycpu $end
$var wire 3 - ALUOP [2:0] $end
$var wire 1 . BRANCH $end
$var wire 1 / BRANCH_TAKEN $end
$var wire 1 0 CLK $end
$var wire 1 1 IMM $end
$var wire 32 2 INSTRUCTION [31:0] $end
$var wire 1 3 JUMP $end
$var wire 8 4 OUT1 [7:0] $end
$var wire 8 5 OUT2 [7:0] $end
$var wire 8 6 OUT2_1 [7:0] $end
$var wire 8 7 OUT2_2 [7:0] $end
$var wire 32 8 PCvalue [31:0] $end
$var wire 1 9 RESET $end
$var wire 8 : RESULT [7:0] $end
$var wire 1 ; SEL $end
$var wire 1 < SUB_ADD $end
$var wire 1 = WRITEENABLE $end
$var wire 1 > ZERO $end
$var reg 8 ? IMMEDIATE [7:0] $end
$var reg 32 @ IMMEDIATE_JB [31:0] $end
$var reg 3 A INADDRESS [2:0] $end
$var reg 8 B OPCODE [7:0] $end
$var reg 8 C OUT2_2s [7:0] $end
$var reg 32 D PC [31:0] $end
$var reg 32 E PCregister [31:0] $end
$var reg 32 F PCregister_JB [31:0] $end
$var reg 3 G READREG1 [2:0] $end
$var reg 3 H READREG2 [2:0] $end
$scope module mux_branch $end
$var wire 32 I input1 [31:0] $end
$var wire 32 J input2 [31:0] $end
$var wire 1 ; select $end
$var reg 32 K output1 [31:0] $end
$upscope $end
$scope module CU $end
$var wire 8 L OPCODE [7:0] $end
$var reg 3 M ALUOP [2:0] $end
$var reg 1 N BRANCH $end
$var reg 1 O IMM $end
$var reg 1 P JUMP $end
$var reg 1 Q SUB_ADD $end
$var reg 1 R WRITEENABLE $end
$upscope $end
$scope module register $end
$var wire 1 0 CLK $end
$var wire 8 S IN [7:0] $end
$var wire 3 T INADDRESS [2:0] $end
$var wire 3 U OUT1ADDRESS [2:0] $end
$var wire 3 V OUT2ADDRESS [2:0] $end
$var wire 1 9 RESET $end
$var wire 1 = WRITE $end
$var reg 8 W OUT1 [7:0] $end
$var reg 8 X OUT2 [7:0] $end
$var integer 32 Y i [31:0] $end
$upscope $end
$scope module Mux1 $end
$var wire 8 Z input1 [7:0] $end
$var wire 8 [ input2 [7:0] $end
$var wire 1 < select $end
$var reg 8 \ output1 [7:0] $end
$upscope $end
$scope module Mux2 $end
$var wire 8 ] input1 [7:0] $end
$var wire 8 ^ input2 [7:0] $end
$var wire 1 1 select $end
$var reg 8 _ output1 [7:0] $end
$upscope $end
$scope module ALU $end
$var wire 8 ` AddOut [7:0] $end
$var wire 8 a AndOut [7:0] $end
$var wire 8 b DATA1 [7:0] $end
$var wire 8 c DATA2 [7:0] $end
$var wire 8 d ForwardOut [7:0] $end
$var wire 8 e MultOut [7:0] $end
$var wire 8 f OrOut [7:0] $end
$var wire 8 g RESULT [7:0] $end
$var wire 3 h SELECT [2:0] $end
$var wire 1 > ZERO $end
$var wire 8 i f [7:0] $end
$var wire 8 j g [7:0] $end
$var wire 8 k h [7:0] $end
$var wire 8 l out [7:0] $end
$scope module F1 $end
$var wire 8 m DATA2 [7:0] $end
$var wire 8 n out [7:0] $end
$upscope $end
$scope module A1 $end
$var wire 8 o DATA1 [7:0] $end
$var wire 8 p DATA2 [7:0] $end
$var wire 8 q carry [7:0] $end
$var wire 8 r out [7:0] $end
$upscope $end
$scope module A2 $end
$var wire 8 s DATA1 [7:0] $end
$var wire 8 t DATA2 [7:0] $end
$var wire 8 u out [7:0] $end
$upscope $end
$scope module O1 $end
$var wire 8 v DATA1 [7:0] $end
$var wire 8 w DATA2 [7:0] $end
$var wire 8 x out [7:0] $end
$upscope $end
$scope module M1 $end
$var wire 8 y AddOut [7:0] $end
$var wire 8 z AndOut [7:0] $end
$var wire 8 { ForwardOut [7:0] $end
$var wire 8 | MultOut [7:0] $end
$var wire 8 } OrOut [7:0] $end
$var wire 3 ~ SELECT [2:0] $end
$var wire 8 !" f [7:0] $end
$var wire 8 "" g [7:0] $end
$var wire 8 #" h [7:0] $end
$var reg 8 $" out [7:0] $end
$upscope $end
$scope module BEQ $end
$var wire 8 %" RESULT [7:0] $end
$var wire 3 &" SELECT [2:0] $end
$var reg 1 '" ZERO $end
$upscope $end
$upscope $end
$upscope $end
$upscope $end
$enddefinitions $end
#0
$dumpvars
x'"
bx &"
bx %"
bx $"
bz #"
bz ""
bz !"
bx ~
bx }
bz |
bx {
bx z
bx y
bx x
bx w
bx v
bx u
bx t
bx s
bx r
bx q
bx p
bx o
bx n
bx m
bx l
bz k
bz j
bz i
bx h
bx g
bx f
bz e
bx d
bx c
bx b
bx a
bx `
bx _
bx ^
bx ]
bx \
bx [
bx Z
b1000 Y
bx X
bx W
bx V
bx U
bx T
bx S
xR
xQ
xP
xO
xN
bx M
bx L
bx K
bx J
bx I
bx H
bx G
bx F
bx E
bx D
bx C
bx B
bx A
bx @
bx ?
x>
x=
x<
x;
bx :
09
bx 8
bx 7
bx 6
bx 5
bx 4
x3
bx 2
x1
00
x/
x.
bx -
0,
bx +
0*
bx )
bx (
bx '
bx &
bx %
bx $
bx #
bx "
bx !
$end
#2
1,
19
#4
1*
10
#5
b0 (
b0 '
b0 &
b0 %
b0 $
b0 #
b0 "
b0 !
b1000 Y
b0 D
b0 )
#6
b100 E
b100 I
#7
0R
0=
b10 @
b10 ?
b10 ^
b10 H
b10 V
b0 G
b0 U
b10 A
b10 T
b0 B
b0 L
b100000000000000010 +
b100000000000000010 2
0,
09
#8
b100 K
b100 8
0;
0/
b10 _
b10 7
b10 c
b10 m
b10 p
b10 t
b10 w
0'"
0>
1R
1=
0P
03
0N
0.
1O
11
0Q
0<
b0 M
b0 -
b0 h
b0 ~
b0 &"
0*
00
#9
b10 $"
b10 l
b10 :
b10 S
b10 g
b10 %"
b0 \
b0 6
b0 ]
b0x0 a
b0x0 u
b0x0 z
bx1x f
bx1x x
bx1x }
b10 d
b10 n
b10 {
b0 X
b0 5
b0 Z
b0 W
b0 4
b0 b
b0 o
b0 s
b0 v
b1100 F
b1100 J
#10
b0 C
b0 [
b0 a
b0 u
b0 z
b10 f
b10 x
b10 }
#11
b10 `
b10 r
b10 y
b0 q
#12
1*
10
#13
b100 D
b100 )
b10 #
#14
b1000 K
b1000 8
b1000 E
b1000 I
#15
b0 _
b0 7
b0 c
b0 m
b0 p
b0 t
b0 w
b110 @
b0 ?
b0 ^
b0 H
b0 V
b110 A
b110 T
b10 \
b10 6
b10 ]
b1100000000000000000 +
b1100000000000000000 2
b10 X
b10 5
b10 Z
#16
b0 $"
b0 l
b0 :
b0 S
b0 g
b0 %"
b0 f
b0 x
b0 }
b0 d
b0 n
b0 {
b11111110 C
b11111110 [
0*
00
#17
b0 \
b0 6
b0 ]
b0 `
b0 r
b0 y
b0 X
b0 5
b0 Z
b100000 F
b100000 J
#18
b0 C
b0 [
#20
1*
10
#21
b0 '
b1000 D
b1000 )
#22
b1100 K
b1100 8
b1100 E
b1100 I
#23
b1010 _
b1010 7
b1010 c
b1010 m
b1010 p
b1010 t
b1010 w
b1 @
b1010 ?
b1010 ^
b10 H
b10 V
b1 A
b1 T
b10000000000001010 +
b10000000000001010 2
#24
b1010 $"
b1010 l
b1010 :
b1010 S
b1010 g
b1010 %"
b1010 f
b1010 x
b1010 }
b1010 d
b1010 n
b1010 {
0*
00
#25
b1010 `
b1010 r
b1010 y
b10 \
b10 6
b10 ]
b10 X
b10 5
b10 Z
b10000 F
b10000 J
#26
b11111110 C
b11111110 [
#28
1*
10
#29
b1100 D
b1100 )
b1010 "
#30
b10000 K
b10000 8
b10000 E
b10000 I
#31
b10 _
b10 7
b10 c
b10 m
b10 p
b10 t
b10 w
0R
0=
b110 @
b10 ?
b10 ^
b110 G
b110 U
b110 A
b110 T
b10 B
b10 L
b10000001100000011000000010 +
b10000001100000011000000010 2
#32
b10 f
b10 x
b10 }
b10 d
b10 n
b10 {
1R
1=
0O
01
b1 M
b1 -
b1 h
b1 ~
b1 &"
0*
00
#33
b10 $"
b10 l
b10 :
b10 S
b10 g
b10 %"
b10 `
b10 r
b10 y
b101000 F
b101000 J
#36
1*
10
#37
b10 '
b10000 D
b10000 )
#38
b10100 K
b10100 8
b10100 E
b10100 I
#39
0R
0=
b1 @
b1 ?
b1 ^
b1 H
b1 V
b1 A
b1 T
b111 B
b111 L
b10 W
b10 4
b10 b
b10 o
b10 s
b10 v
b111000000010000011000000001 +
b111000000010000011000000001 2
#40
b11111110 _
b11111110 7
b11111110 c
b11111110 m
b11111110 p
b11111110 t
b11111110 w
b11111110 \
b11111110 6
b11111110 ]
1N
1.
1Q
1<
b10 a
b10 u
b10 z
0*
00
#41
b11111110 f
b11111110 x
b11111110 }
b11111110 d
b11111110 n
b11111110 {
b1010 X
b1010 5
b1010 Z
b11000 F
b11000 J
#42
b11000 K
b11000 8
1;
1/
1'"
1>
b11110110 _
b11110110 7
b11110110 c
b11110110 m
b11110110 p
b11110110 t
b11110110 w
b0 $"
b0 l
b0 :
b0 S
b0 g
b0 %"
b11110110 \
b11110110 6
b11110110 ]
b0 `
b0 r
b0 y
b11110110 C
b11110110 [
#43
b11110110 f
b11110110 x
b11110110 }
b11110110 d
b11110110 n
b11110110 {
#44
b10100 K
b10100 8
0;
0/
0'"
0>
b11111000 $"
b11111000 l
b11111000 :
b11111000 S
b11111000 g
b11111000 %"
b11111000 `
b11111000 r
b11111000 y
b11111111 q
1*
10
#45
b10100 D
b10100 )
#46
b11000 K
b11000 8
b11000 E
b11000 I
#47
b11111111111111111111111111111101 @
b0 ?
b0 ^
b0 H
b0 V
b0 G
b0 U
b101 A
b101 T
b110 B
b110 L
b110111111010000000000000000 +
b110111111010000000000000000 2
#48
b1010 _
b1010 7
b1010 c
b1010 m
b1010 p
b1010 t
b1010 w
1;
b1010 \
b1010 6
b1010 ]
bx $"
bx l
bx :
bx S
bx g
bx %"
1P
13
0N
0.
0Q
0<
bx M
bx -
bx h
bx ~
bx &"
0*
00
#49
b0 _
b0 7
b0 c
b0 m
b0 p
b0 t
b0 w
b0 \
b0 6
b0 ]
b1100 K
b1100 8
b1010 f
b1010 x
b1010 }
b1010 d
b1010 n
b1010 {
b0 X
b0 5
b0 Z
b0 W
b0 4
b0 b
b0 o
b0 s
b0 v
b1100 F
b1100 J
#50
b0 f
b0 x
b0 }
b0 d
b0 n
b0 {
b0 C
b0 [
b0 a
b0 u
b0 z
#51
b0 `
b0 r
b0 y
b0 q
#52
1*
10
#53
b1100 D
b1100 )
#54
b10000 E
b10000 I
#55
b110 @
b10 ?
b10 ^
b10 H
b10 V
b110 G
b110 U
b110 A
b110 T
b10 B
b10 L
b10000001100000011000000010 +
b10000001100000011000000010 2
#56
b10000 K
b10000 8
0;
1'"
1>
b0 $"
b0 l
b0 :
b0 S
b0 g
b0 %"
1R
1=
0P
03
b1 M
b1 -
b1 h
b1 ~
b1 &"
0*
00
#57
b10 _
b10 7
b10 c
b10 m
b10 p
b10 t
b10 w
b10 \
b10 6
b10 ]
b10 X
b10 5
b10 Z
b10 W
b10 4
b10 b
b10 o
b10 s
b10 v
b101000 F
b101000 J
#58
b10 a
b10 u
b10 z
b10 d
b10 n
b10 {
b11111110 C
b11111110 [
b10 f
b10 x
b10 }
#59
0'"
0>
b100 $"
b100 l
b100 :
b100 S
b100 g
b100 %"
b100 `
b100 r
b100 y
#60
1*
10
#61
b100 '
b10000 D
b10000 )
#62
b10100 K
b10100 8
b10100 E
b10100 I
#63
0R
0=
b1 @
b1 ?
b1 ^
b1 H
b1 V
b1 A
b1 T
b111 B
b111 L
b100 W
b100 4
b100 b
b100 o
b100 s
b100 v
b111000000010000011000000001 +
b111000000010000011000000001 2
#64
b11111110 _
b11111110 7
b11111110 c
b11111110 m
b11111110 p
b11111110 t
b11111110 w
b11111110 \
b11111110 6
b11111110 ]
1N
1.
1Q
1<
b0 a
b0 u
b0 z
b110 f
b110 x
b110 }
0*
00
#65
b100 a
b100 u
b100 z
b11111110 f
b11111110 x
b11111110 }
b11111110 d
b11111110 n
b11111110 {
b1010 X
b1010 5
b1010 Z
b11000 F
b11000 J
#66
b11110110 _
b11110110 7
b11110110 c
b11110110 m
b11110110 p
b11110110 t
b11110110 w
b10 $"
b10 l
b10 :
b10 S
b10 g
b10 %"
b11110110 \
b11110110 6
b11110110 ]
b10 `
b10 r
b10 y
b11110110 C
b11110110 [
#67
b11110110 f
b11110110 x
b11110110 }
b11110110 d
b11110110 n
b11110110 {
#68
b11111010 $"
b11111010 l
b11111010 :
b11111010 S
b11111010 g
b11111010 %"
b11111010 `
b11111010 r
b11111010 y
b11111111 q
1*
10
#69
b10100 D
b10100 )
#70
b11000 K
b11000 8
b11000 E
b11000 I
#71
b11111111111111111111111111111101 @
b0 ?
b0 ^
b0 H
b0 V
b0 G
b0 U
b101 A
b101 T
b110 B
b110 L
b110111111010000000000000000 +
b110111111010000000000000000 2
#72
b1010 _
b1010 7
b1010 c
b1010 m
b1010 p
b1010 t
b1010 w
1;
b1010 \
b1010 6
b1010 ]
bx $"
bx l
bx :
bx S
bx g
bx %"
1P
13
0N
0.
0Q
0<
bx M
bx -
bx h
bx ~
bx &"
0*
00
#73
b0 _
b0 7
b0 c
b0 m
b0 p
b0 t
b0 w
b0 \
b0 6
b0 ]
b1100 K
b1100 8
b0 a
b0 u
b0 z
b1110 f
b1110 x
b1110 }
b1010 d
b1010 n
b1010 {
b0 X
b0 5
b0 Z
b0 W
b0 4
b0 b
b0 o
b0 s
b0 v
b1100 F
b1100 J
#74
b0 d
b0 n
b0 {
b0 C
b0 [
b0 f
b0 x
b0 }
